buildlog_parser/__init__.py
buildlog_parser/main.py
buildlog_parser/prompts.py
buildlog_parser-2025.12.22082056.dist-info/METADATA
buildlog_parser-2025.12.22082056.dist-info/WHEEL
buildlog_parser-2025.12.22082056.dist-info/top_level.txt
buildlog_parser-2025.12.22082056.dist-info/RECORD
