Metadata-Version: 2.4
Name: buildlog-parser
Version: 2025.12.22082056
Summary: buildlog-parser extracts structured log data, categorizing status, errors, warnings, timestamps for easy CI analysis.
Author-email: buildlog-parser <hi@eugene.plus>
License: MIT
Project-URL: Homepage, https://github.com/chigwell/buildlog-parser
Requires-Python: >=3.9
Requires-Dist: langchain-llm7>=0.0.0
Requires-Dist: llmatch-messages>=0.0.0
Requires-Dist: langchain-core>=0.3.0
